tracspamfilter/__init__.py
tracspamfilter/accountadapter.py
tracspamfilter/adapters.py
tracspamfilter/admin.py
tracspamfilter/adminreport.py
tracspamfilter/adminusers.py
tracspamfilter/api.py
tracspamfilter/filtersystem.py
tracspamfilter/model.py
tracspamfilter/report.py
tracspamfilter/timeoutserverproxy.py
tracspamfilter/users.py
tracspamfilter/captcha/__init__.py
tracspamfilter/captcha/admin.py
tracspamfilter/captcha/api.py
tracspamfilter/captcha/expression.py
tracspamfilter/captcha/image.py
tracspamfilter/captcha/keycaptcha.py
tracspamfilter/captcha/rand.py
tracspamfilter/captcha/recaptcha2.py
tracspamfilter/filters/__init__.py
tracspamfilter/filters/akismet.py
tracspamfilter/filters/bayes.py
tracspamfilter/filters/blogspam.py
tracspamfilter/filters/botscout.py
tracspamfilter/filters/extlinks.py
tracspamfilter/filters/fspamlist.py
tracspamfilter/filters/httpbl.py
tracspamfilter/filters/ip_blacklist.py
tracspamfilter/filters/ip_regex.py
tracspamfilter/filters/ip_throttle.py
tracspamfilter/filters/regex.py
tracspamfilter/filters/registration.py
tracspamfilter/filters/session.py
tracspamfilter/filters/stopforumspam.py
tracspamfilter/filters/trapfield.py
tracspamfilter/filters/url_blacklist.py
tracspamfilter/fonts/vera.ttf
tracspamfilter/htdocs/admin.css
tracspamfilter/htdocs/adminbayes.js
tracspamfilter/htdocs/adminconfig.js
tracspamfilter/htdocs/adminexternal.js
tracspamfilter/htdocs/adminmonitor.js
tracspamfilter/htdocs/no.gif
tracspamfilter/htdocs/reportspam.js
tracspamfilter/htdocs/yes.gif
tracspamfilter/locale/cs/LC_MESSAGES/tracspamfilter.mo
tracspamfilter/locale/de/LC_MESSAGES/tracspamfilter.mo
tracspamfilter/locale/fr/LC_MESSAGES/tracspamfilter.mo
tracspamfilter/locale/ja/LC_MESSAGES/tracspamfilter.mo
tracspamfilter/locale/ko/LC_MESSAGES/tracspamfilter.mo
tracspamfilter/templates/admin_bayes.html
tracspamfilter/templates/admin_captcha.html
tracspamfilter/templates/admin_external.html
tracspamfilter/templates/admin_report.html
TracSpamFilter-1.2.7.dist-info/COPYING
TracSpamFilter-1.2.7.dist-info/METADATA
TracSpamFilter-1.2.7.dist-info/WHEEL
TracSpamFilter-1.2.7.dist-info/entry_points.txt
TracSpamFilter-1.2.7.dist-info/top_level.txt
TracSpamFilter-1.2.7.dist-info/RECORD
