Metadata-Version: 2.1
Name: TracSpamFilter
Version: 1.2.7
Summary: Plugin for spam filtering
Home-page: https://trac.edgewall.org/wiki/SpamFilter
Author: Edgewall Software
Author-email: info@edgewall.com
License: BSD
Download-URL: https://trac.edgewall.org/wiki/SpamFilter
Keywords: trac plugin
Platform: UNKNOWN
Classifier: Framework :: Trac
Classifier: License :: OSI Approved :: BSD License
Requires-Dist: Trac
Provides-Extra: account
Requires-Dist: TracAccountManager (>=0.4) ; extra == 'account'
Provides-Extra: dns
Requires-Dist: dnspython (>=1.3.5) ; extra == 'dns'
Provides-Extra: httplib2
Requires-Dist: httplib2 ; extra == 'httplib2'
Provides-Extra: oauth
Requires-Dist: oauth2 ; extra == 'oauth'
Provides-Extra: pillow
Requires-Dist: pillow (>=2) ; extra == 'pillow'
Provides-Extra: spambayes
Requires-Dist: spambayes ; extra == 'spambayes'
